efficient_linear_decoding/__init__.py
efficient_linear_decoding/efficient_linear_decoding.py
efficient_linear_decoding/methods/BlockBased.py
efficient_linear_decoding/methods/FleetAttention.py
efficient_linear_decoding/methods/Recursion.py
efficient_linear_decoding/methods/RowBased.py
efficient_linear_decoding/methods/__init__.py
efficient_linear_decoding/methods/causal_dot_product.py
efficient_linear_decoding/methods/causal_product_cuda.cu
efficient_linear_decoding/methods/causal_product_cuda_with_decay_fp16.cu
efficient_linear_decoding/methods/causal_product_cuda_with_decay_fp32.cu
efficient_linear_decoding/methods/lightningAttention2.py
efficient_linear_decoding/methods/lightningAttention2_torch.py
efficient_linear_decoding/methods/linear_attn.py
efficient_linear_decoding-0.0.6.dist-info/LICENSE
efficient_linear_decoding-0.0.6.dist-info/METADATA
efficient_linear_decoding-0.0.6.dist-info/WHEEL
efficient_linear_decoding-0.0.6.dist-info/top_level.txt
efficient_linear_decoding-0.0.6.dist-info/RECORD
